{ "columns":5,
 "image":"saacred_root_magic.png",
 "imageheight":1536,
 "imagewidth":3520,
 "leftOffset":{
    "x": -64,
    "y": 192
 },
 "margin":0,
 "name":"saacred_root_magic",
 "spacing":0,
 "tilecount":15,
 "tiledversion":"1.9.1",
 "tileheight":512,
 "tiles":[
        {
         "animation":[
                {
                 "duration":380,
                 "tileid":0
                }, 
                {
                 "duration":380,
                 "tileid":1
                }, 
                {
                 "duration":380,
                 "tileid":2
                }, 
                {
                 "duration":380,
                 "tileid":3
                }, 
                {
                 "duration":380,
                 "tileid":4
                }, 
                {
                 "duration":380,
                 "tileid":5
                }, 
                {
                 "duration":380,
                 "tileid":6
                }, 
                {
                 "duration":380,
                 "tileid":7
                }, 
                {
                 "duration":380,
                 "tileid":8
                }, 
                {
                 "duration":380,
                 "tileid":9
                }, 
                {
                 "duration":380,
                 "tileid":10
                }, 
                {
                 "duration":380,
                 "tileid":11
                }, 
                {
                 "duration":380,
                 "tileid":12
                }, 
                {
                 "duration":380,
                 "tileid":13
                }],
         "id":0
        }],
 "tilewidth":704,
 "type":"tileset",
 "version":"1.8"
}